geddit/__init__.py
geddit-2.1.6.dist-info/METADATA
geddit-2.1.6.dist-info/WHEEL
geddit-2.1.6.dist-info/licenses/LICENSE
geddit-2.1.6.dist-info/RECORD
