Metadata-Version: 2.4
Name: geddit
Version: 2.1.6
Summary: Zero-configuration fetching of configuration resources
License-File: LICENSE
Author: University of Cambridge Information Services
Author-email: devops+geddit@uis.cam.ac.uk
Requires-Python: >=3.9,<4.0
Classifier: Programming Language :: Python :: 3
Classifier: Programming Language :: Python :: 3.9
Classifier: Programming Language :: Python :: 3.10
Classifier: Programming Language :: Python :: 3.11
Classifier: Programming Language :: Python :: 3.12
Classifier: Programming Language :: Python :: 3.13
Classifier: Programming Language :: Python :: 3.14
Requires-Dist: google-cloud-secret-manager (>=2.7,<3.0)
Requires-Dist: google-cloud-storage (>=3.8,<3.9)
Requires-Dist: requests (>=2.31.0,<3.0.0)
